pyminimap2/_pyminimap2.c
pyminimap2/_core.cpython-310-x86_64-linux-gnu.so
pyminimap2/__init__.py
pyminimap2-2.30.3.dist-info/WHEEL
pyminimap2-2.30.3.dist-info/top_level.txt
pyminimap2-2.30.3.dist-info/METADATA
pyminimap2-2.30.3.dist-info/RECORD
