Metadata-Version: 2.4
Name: pyminimap2
Version: 2.30.3
Summary: Python wrapper for minimap2 with stdout/stderr capture
License: MIT
Project-URL: Homepage, https://github.com/TheFangLab/pyminimap2
Project-URL: Repository, https://github.com/TheFangLab/pyminimap2
Project-URL: Issues, https://github.com/TheFangLab/pyminimap2/issues
Keywords: minimap2,bioinformatics,sequence alignment,genomics
Classifier: Development Status :: 4 - Beta
Classifier: Intended Audience :: Science/Research
Classifier: License :: OSI Approved :: MIT License
Classifier: Operating System :: POSIX :: Linux
Classifier: Programming Language :: Python :: 3
Classifier: Programming Language :: Python :: 3.9
Classifier: Programming Language :: Python :: 3.10
Classifier: Programming Language :: Python :: 3.11
Classifier: Programming Language :: Python :: 3.12
Classifier: Programming Language :: Python :: 3.13
Classifier: Programming Language :: C
Classifier: Topic :: Scientific/Engineering :: Bio-Informatics
Requires-Python: >=3.9
